<?xml version="1.0" encoding="ISO-8859-1"?>
<renderable_objects>
	<mesh_instance name="Box001" core_name="Box001" pos="TranslationToRH()" yaw="[0,0,0]" pitch="0.0" roll="0.0" visible="GetYaw()">
	<mesh_instance name="Box002" core_name="Box002" pos="TranslationToRH()" yaw="[3.88479,0,0]" pitch="0.0" roll="0.0" visible="GetYaw()">
	<mesh_instance name="Box003" core_name="Box003" pos="TranslationToRH()" yaw="[7.76958,0,0]" pitch="0.0" roll="0.0" visible="GetYaw()">
	<mesh_instance name="Box004" core_name="Box004" pos="TranslationToRH()" yaw="[11.6544,0,0]" pitch="0.0" roll="0.0" visible="GetYaw()">
	<mesh_instance name="Box005" core_name="Box005" pos="TranslationToRH()" yaw="[0,3.4845,0]" pitch="0.0" roll="0.0" visible="GetYaw()">
	<mesh_instance name="Box006" core_name="Box006" pos="TranslationToRH()" yaw="[0,6.96901,0]" pitch="0.0" roll="0.0" visible="GetYaw()">
	<mesh_instance name="Box007" core_name="Box007" pos="TranslationToRH()" yaw="[4.03877,3.4845,0]" pitch="0.0" roll="0.0" visible="GetYaw()">
	<mesh_instance name="Box008" core_name="Box008" pos="TranslationToRH()" yaw="[6.85453,3.79147,0]" pitch="0.0" roll="0.0" visible="GetYaw()">
</renderable_objects>
